pyltx/__init__.py
pyltx/figure.py
pyltx/math.py
pyltx/table.py
pyltx/text.py
pyltx/utils.py
pyltx-0.1.4.dist-info/LICENSE
pyltx-0.1.4.dist-info/METADATA
pyltx-0.1.4.dist-info/WHEEL
pyltx-0.1.4.dist-info/top_level.txt
pyltx-0.1.4.dist-info/RECORD
