Metadata-Version: 2.1
Name: pyltx
Version: 0.1.4
Summary: LaTeX generation for tables, math and figures
Home-page: https://github.com/matiyau/pyltx
Author: Nishad Mandlik
Author-email: mandliksg@gmail.com
License: UNKNOWN
Project-URL: Documentation, https://pyltx.rtfd.io
Project-URL: Bug Tracker, https://github.com/matiyau/pyltx/issues
Platform: UNKNOWN
Classifier: Programming Language :: Python :: 3
Classifier: License :: OSI Approved :: MIT License
Classifier: Operating System :: OS Independent
Requires-Python: >=3.6
